generaltags
